itn/__init__.py
itn/__main__.py
itn/main.py
itn/zh_itn_tagger.fst
itn/zh_itn_verbalizer.fst
itn/chinese/__init__.py
itn/chinese/inverse_normalizer.py
itn/chinese/data/date/dd.tsv
itn/chinese/data/date/mm.tsv
itn/chinese/data/default/blacklist.tsv
itn/chinese/data/default/whitelist.tsv
itn/chinese/data/license_plate/province.tsv
itn/chinese/data/math/operator.tsv
itn/chinese/data/measure/units_en.tsv
itn/chinese/data/measure/units_zh.tsv
itn/chinese/data/money/code.tsv
itn/chinese/data/money/symbol.tsv
itn/chinese/data/number/digit.tsv
itn/chinese/data/number/digit_zh.tsv
itn/chinese/data/number/dot.tsv
itn/chinese/data/number/sign.tsv
itn/chinese/data/number/special_dash.tsv
itn/chinese/data/number/special_tilde.tsv
itn/chinese/data/number/zero.tsv
itn/chinese/data/time/hour.tsv
itn/chinese/data/time/minute.tsv
itn/chinese/data/time/noon.tsv
itn/chinese/data/time/second.tsv
itn/chinese/rules/__init__.py
itn/chinese/rules/cardinal.py
itn/chinese/rules/char.py
itn/chinese/rules/date.py
itn/chinese/rules/fraction.py
itn/chinese/rules/license_plate.py
itn/chinese/rules/math.py
itn/chinese/rules/measure.py
itn/chinese/rules/money.py
itn/chinese/rules/postprocessor.py
itn/chinese/rules/time.py
itn/chinese/rules/whitelist.py
itn/chinese/test/__init__.py
itn/chinese/test/normalizer_test.py
itn/chinese/test/utils.py
tn/__init__.py
tn/__main__.py
tn/en_tn_tagger.fst
tn/en_tn_verbalizer.fst
tn/main.py
tn/processor.py
tn/token_parser.py
tn/utils.py
tn/zh_tn_tagger.fst
tn/zh_tn_verbalizer.fst
tn/chinese/__init__.py
tn/chinese/normalizer.py
tn/chinese/data/char/charset_extension.tsv
tn/chinese/data/char/charset_national_standard_2013_8105.tsv
tn/chinese/data/char/fullwidth_to_halfwidth.tsv
tn/chinese/data/char/punctuations_zh.tsv
tn/chinese/data/char/traditional_to_simple.tsv
tn/chinese/data/date/d.tsv
tn/chinese/data/date/dd.tsv
tn/chinese/data/date/m.tsv
tn/chinese/data/date/mm.tsv
tn/chinese/data/default/blacklist.tsv
tn/chinese/data/default/whitelist.tsv
WeTextProcessing-1.0.4.1.dist-info/LICENSE
WeTextProcessing-1.0.4.1.dist-info/METADATA
WeTextProcessing-1.0.4.1.dist-info/WHEEL
WeTextProcessing-1.0.4.1.dist-info/entry_points.txt
WeTextProcessing-1.0.4.1.dist-info/top_level.txt
WeTextProcessing-1.0.4.1.dist-info/RECORD
