Metadata-Version: 2.1
Name: WeTextProcessing
Version: 1.0.4.1
Summary: WeTextProcessing, including TN & ITN
Home-page: https://github.com/wenet-e2e/WeTextProcessing
Author: Zhendong Peng, Xingchen Song
Author-email: pzd17@tsinghua.org.cn, sxc19@tsinghua.org.cn
License: UNKNOWN
Platform: UNKNOWN
Classifier: Programming Language :: Python :: 3
Classifier: Operating System :: OS Independent
Classifier: Topic :: Scientific/Engineering :: Artificial Intelligence
License-File: LICENSE
Requires-Dist: pynini ==2.1.6
Requires-Dist: importlib-resources
